{
  "global": [
    {
      "title": "Calculators - M3DP",
      "url": "/calc/",
      "views": 384
    },
    {
      "title": "Settings Assistant",
      "url": "/settings/",
      "views": 298
    },
    {
      "title": "FDM Cost Calculator - Minimal 3DP",
      "url": "/fdm-cost/",
      "views": 281
    },
    {
      "title": "Minimal 3DP Platform",
      "url": "/calc/shrinkage",
      "views": 132
    },
    {
      "title": "FDM Filament Finder - M3DP",
      "url": "/filament/",
      "views": 111
    }
  ],
  "blog": [],
  "tools": [
    {
      "title": "Brick Effect Processor - M3DP",
      "url": "/tools/bricklayers/",
      "views": 88
    },
    {
      "title": "Filament Deals | Minimal 3DP",
      "url": "/tools/deals/",
      "views": 11
    }
  ],
  "projects": []
}